VL53L1X.py
vl53l1x_python.so
VL53L1X-0.0.4.dist-info/METADATA
VL53L1X-0.0.4.dist-info/WHEEL
VL53L1X-0.0.4.dist-info/top_level.txt
VL53L1X-0.0.4.dist-info/RECORD
