Metadata-Version: 2.1
Name: VL53L1X
Version: 0.0.4
Summary: vl53l1x distance sensor driver for Raspberry Pi
Home-page: https://github.com/pimoroni/vl53l1x-python
Maintainer: Phil Howard
Maintainer-email: phil@pimoroni.com
License: UNKNOWN
Platform: UNKNOWN
Requires: smbus2
